{"stats":{"minecraft:dropped":{"minecraft:cooked_beef":1},"minecraft:custom":{"minecraft:time_since_rest":5738,"minecraft:crouch_one_cm":65,"minecraft:sprint_one_cm":15223,"minecraft:play_time":8903,"minecraft:deaths":1,"minecraft:damage_taken":586,"minecraft:walk_one_cm":28935,"minecraft:sneak_time":6,"minecraft:drop":1,"minecraft:jump":146,"minecraft:damage_dealt":52,"minecraft:leave_game":4,"minecraft:time_since_death":5697,"minecraft:total_world_time":8903,"minecraft:fall_one_cm":2552,"minecraft:fly_one_cm":44520},"minecraft:picked_up":{"minecraft:iron_axe":1,"minecraft:cooked_beef":2,"minecraft:wheat_seeds":1,"minecraft:potion":1,"minecraft:spruce_log":6,"minecraft:spider_eye":1,"minecraft:mossy_cobblestone":1},"minecraft:used":{"minecraft:potion":1,"minecraft:cooked_beef":1},"minecraft:mined":{"minecraft:grass":1,"minecraft:spruce_leaves":1,"minecraft:spruce_log":6}},"DataVersion":3465}